<?xml version="1.0" encoding="utf-8"?>
<LanguageData>

  <GrenadierDestructive.label>grenadier</GrenadierDestructive.label>
  <GrenadierDestructive.labelPlural>grenadiers</GrenadierDestructive.labelPlural>

  <GrenadierEMP.label>EMP grenadier</GrenadierEMP.label>
  <GrenadierEMP.labelPlural>EMP grenadiers</GrenadierEMP.labelPlural>

  <MercenaryGunner.label>mercenary gunner</MercenaryGunner.label>
  <MercenaryGunner.labelPlural>mercenary gunners</MercenaryGunner.labelPlural>

  <MercenarySniper.label>mercenary sniper</MercenarySniper.label>
  <MercenarySniper.labelPlural>mercenary snipers</MercenarySniper.labelPlural>

  <MercenarySlasher.label>mercenary slasher</MercenarySlasher.label>
  <MercenarySlasher.labelPlural>mercenary slashers</MercenarySlasher.labelPlural>

  <MercenaryHeavy.label>heavy mercenary</MercenaryHeavy.label>
  <MercenaryHeavy.labelPlural>heavy mercenaries</MercenaryHeavy.labelPlural>

  <PirateBoss.label>boss</PirateBoss.label>
  <PirateBoss.labelPlural>bosses</PirateBoss.labelPlural>

  <MercenaryElite.label>elite mercenary</MercenaryElite.label>
  <MercenaryElite.labelPlural>elite mercenaries</MercenaryElite.labelPlural>


</LanguageData>